{
  "coverage": "100%",
  "expectCount": 1289,
  "actualCount": 1289,
  "files": {
    "src/konpeito.js": {
      "expectCount": 11,
      "actualCount": 11,
      "undocumentLines": []
    },
    "src/math/core/base/KonpeitoFloat.js": {
      "expectCount": 49,
      "actualCount": 49,
      "undocumentLines": []
    },
    "src/math/core/base/KonpeitoInteger.js": {
      "expectCount": 71,
      "actualCount": 71,
      "undocumentLines": []
    },
    "src/math/core/BigDecimal.js": {
      "expectCount": 186,
      "actualCount": 186,
      "undocumentLines": []
    },
    "src/math/core/BigInteger.js": {
      "expectCount": 130,
      "actualCount": 130,
      "undocumentLines": []
    },
    "src/math/core/Complex.js": {
      "expectCount": 183,
      "actualCount": 183,
      "undocumentLines": []
    },
    "src/math/core/context/MathContext.js": {
      "expectCount": 17,
      "actualCount": 17,
      "undocumentLines": []
    },
    "src/math/core/context/RoundingMode.js": {
      "expectCount": 37,
      "actualCount": 37,
      "undocumentLines": []
    },
    "src/math/core/Fraction.js": {
      "expectCount": 88,
      "actualCount": 88,
      "undocumentLines": []
    },
    "src/math/core/Matrix.js": {
      "expectCount": 331,
      "actualCount": 331,
      "undocumentLines": []
    },
    "src/math/core/tools/LinearAlgebra.js": {
      "expectCount": 24,
      "actualCount": 24,
      "undocumentLines": []
    },
    "src/math/core/tools/Probability.js": {
      "expectCount": 43,
      "actualCount": 43,
      "undocumentLines": []
    },
    "src/math/core/tools/random/MaximumLengthSequence.js": {
      "expectCount": 9,
      "actualCount": 9,
      "undocumentLines": []
    },
    "src/math/core/tools/random/Xorshift.js": {
      "expectCount": 10,
      "actualCount": 10,
      "undocumentLines": []
    },
    "src/math/core/tools/Random.js": {
      "expectCount": 17,
      "actualCount": 17,
      "undocumentLines": []
    },
    "src/math/core/tools/Signal.js": {
      "expectCount": 59,
      "actualCount": 59,
      "undocumentLines": []
    },
    "src/math/core/tools/Statistics.js": {
      "expectCount": 18,
      "actualCount": 18,
      "undocumentLines": []
    },
    "src/math/tools/DataAnalysis/MultipleRegressionAnalysis.js": {
      "expectCount": 2,
      "actualCount": 2,
      "undocumentLines": []
    },
    "src/math/tools/DataAnalysis.js": {
      "expectCount": 2,
      "actualCount": 2,
      "undocumentLines": []
    },
    "src/math/tools/Polyfill.js": {
      "expectCount": 2,
      "actualCount": 2,
      "undocumentLines": []
    }
  }
}